microservice_template/__init__.py
microservice_template/microservice.py
microservice_template-0.0.6.dist-info/METADATA
microservice_template-0.0.6.dist-info/WHEEL
microservice_template-0.0.6.dist-info/top_level.txt
microservice_template-0.0.6.dist-info/RECORD
