Metadata-Version: 2.1
Name: microservice-template
Version: 0.0.6
Summary: Microservicetemplate
Home-page: UNKNOWN
Author: Pixelfehler
License: UNKNOWN
Keywords: python,microservice
Platform: UNKNOWN
Classifier: Development Status :: 1 - Planning
Classifier: Intended Audience :: Developers
Classifier: Programming Language :: Python :: 3
Classifier: Operating System :: Unix
Classifier: Operating System :: MacOS :: MacOS X
Classifier: Operating System :: Microsoft :: Windows
Requires-Dist: flask
Requires-Dist: flask-cors
